{
  "id": "part-0057",
  "number": 57,
  "arc": 2,
  "titleRu": "Забрезживший свет и тень тревоги",
  "titleJp": "見えた光明と不穏の影",
  "sources": {
    "original": "https://ncode.syosetu.com/n2267be/57/",
    "en_wct": "https://witchculttranslation.com/table-of-content/",
    "other": []
  },
  "paragraphs": [
    {
      "pid": "p57-0001",
      "type": "paragraph",
      "ru": "Полупредрешённые переговоры с Беатрис завершились, и Субару благополучно заручился её содействием."
    },
    {
      "pid": "p57-0002",
      "type": "paragraph",
      "ru": "Не отнять, что итог изрядно опирался на её снисхождение, — но сетовать на собственное бессилие в этой части он отложил на потом."
    },
    {
      "pid": "p57-0003",
      "type": "paragraph",
      "ru": "Цель достигнута, а каяться можно и после. Начни выводить «вот если бы да кабы» прямо посреди дела — конца этому не будет."
    },
    {
      "pid": "p57-0004",
      "type": "paragraph",
      "ru": "Невзначай забеспокоившись о времени, Субару тронул себя за подбородок."
    },
    {
      "pid": "p57-0005",
      "type": "paragraph",
      "ru": "Запретное книгохранилище было наглухо отрезано от внешнего мира, и узнать изнутри, который час снаружи, было нечем. Не стояло здесь даже кристалла-самоцвета вместо часов; в этом смысле живёт она весьма привольно, подумал он, глядя на девочку — хранительницу книгохранилища."
    },
    {
      "pid": "p57-0006",
      "type": "paragraph",
      "ru": "По щетине на подбородке выходило, что с тех пор, как он приводил себя в порядок, прошло около семнадцати часов. Стало быть, сейчас, надо думать, что-то около десяти вечера."
    },
    {
      "pid": "p57-0007",
      "type": "paragraph",
      "ru": "Если вспомнить, что мёртвый сон на коленях у Эмилии начался ещё за полдень, то проспал он просто неприлично долго."
    },
    {
      "pid": "p57-0008",
      "type": "paragraph",
      "ru": "И это при том, что сам же кипятился, мол, ни секунды нельзя терять впустую, — чем больше об этом думаешь, тем безнадёжнее."
    },
    {
      "pid": "p57-0009",
      "type": "paragraph",
      "ru": "Стоит начать копаться в самоуничижении — конца не будет, поэтому Субару перешёл к главному, обращаясь к Беатрис, у которой шкала недовольства явно набралась до краёв."
    },
    {
      "pid": "p57-0010",
      "type": "paragraph",
      "ru": "Насколько он сумеет объяснить ей, не касаясь сути?"
    },
    {
      "pid": "p57-0011",
      "type": "paragraph",
      "ru": "Не теряя бдительности к чёрному маеву, намереваясь разрешать вопрос за вопросом, он начал:"
    },
    {
      "pid": "p57-0012",
      "type": "dialogue",
      "ru": "«…Хочешь подробнее разузнать про заклинателей проклятий?»"
    },
    {
      "pid": "p57-0013",
      "type": "dialogue",
      "ru": "«Ага. В отличие от магов там или заклинателей духов, про то, что есть и такие умельцы, я знаю, а вот дальше — глухо.»"
    },
    {
      "pid": "p57-0014",
      "type": "dialogue",
      "ru": "«Опять ты падок до какой-то несуразицы. Знать про этакую публику — ни на грош проку, кругом одна труха.»"
    },
    {
      "pid": "p57-0015",
      "type": "paragraph",
      "ru": "Как и в тот раз, когда она лишь вскользь об этом обмолвилась, лицо Беатрис, заговорившей о проклятии, было не из светлых. Ей не по нутру было то, как они обходятся с маной, — так она прямо и заявила; но сегодня требовалось вгрызться в это ещё глубже."
    },
    {
      "pid": "p57-0016",
      "type": "dialogue",
      "ru": "«Это ведь, по сути, такое ремесло, которым только людям и пакостишь, верно? Слыхал, на севере, в тамошних краях, оно было в ходу.»"
    },
    {
      "pid": "p57-0017",
      "type": "dialogue",
      "ru": "«Раз уж до такого дознался, так, пожалуй, я тебе и не нужна. — Проклятием можно вселить в жертву хворь, или наложить путы, что запрещают ей определённые поступки, или попросту скосить саму её жизнь… дрянное ремесло, что ни говори.»"
    },
    {
      "pid": "p57-0018",
      "type": "dialogue",
      "ru": "«Ну, оно конечно, всякая вещь — смотря как пользоваться; да только при этакой однобокости и применения-то ей не сыщешь, кроме как другим ножку подставлять.»"
    },
    {
      "pid": "p57-0019",
      "type": "paragraph",
      "ru": "Оттого-то — проклятие. То самое, что так и зовут."
    },
    {
      "pid": "p57-0020",
      "type": "paragraph",
      "ru": "Сверхъестественная сила унижать ближнего — порок, что, видно, способен зародиться в любой культуре, в любом обществе. Вот только чтобы он и впрямь возымел силу, способную воздействовать на других, — такое, надо думать, водится лишь в здешнем мире."
    },
    {
      "pid": "p57-0021",
      "type": "paragraph",
      "ru": "Заклятие в час быка — оно, если приглядеться, тоже из области проклятий."
    },
    {
      "pid": "p57-0022",
      "type": "paragraph",
      "ru": "Размышляя об этом, Субару, чтобы разговорить неохотную на слова Беатрис, подался вперёд:"
    },
    {
      "pid": "p57-0023",
      "type": "dialogue",
      "ru": "«Тогда вот что хочу спросить… от проклятия-то как уберечься?»"
    },
    {
      "pid": "p57-0024",
      "type": "paragraph",
      "ru": "Дать отпор заклинателю проклятий — само по себе дело трудное, покуда не ухватишь, кто он таков. Но всё преимущество, что Субару выгадал в этой обстановке, сводилось к одному: он знает, что нападение будет."
    },
    {
      "pid": "p57-0025",
      "type": "paragraph",
      "ru": "Пусть личность заклинателя и неведома, но раз известно, что он пускает в ход «проклятие», то изыскать средство против него — само собой разумеющийся и здравый ход. Сам себе на удивление — славная мысль."
    },
    {
      "pid": "p57-0026",
      "type": "paragraph",
      "ru": "Однако,"
    },
    {
      "pid": "p57-0027",
      "type": "dialogue",
      "ru": "«Нет такого.»"
    },
    {
      "pid": "p57-0028",
      "type": "dialogue",
      "ru": "«—А?»"
    },
    {
      "pid": "p57-0029",
      "type": "dialogue",
      "ru": "«Способа защититься от единожды сработавшего проклятия не существует. Проклятие являет свою силу и не сгинет, покуда не доведёт порчу над жертвой до самого конца.»"
    },
    {
      "pid": "p57-0030",
      "type": "dialogue",
      "ru": "«Обнуление сопротивления мгновенной смерти, что ли… да это же чистый чит.»"
    },
    {
      "pid": "p57-0031",
      "type": "paragraph",
      "ru": "От бесстрастно изложенных слов Беатрис сердце Субару уже готово было надломиться."
    },
    {
      "pid": "p57-0032",
      "type": "paragraph",
      "ru": "Внезапный удар заклятием, обнуляющим стойкость к мгновенной смерти, — стоит лишь представить, и понятно: при этаких условиях боя на тебя горой обрушатся попрёки."
    },
    {
      "pid": "p57-0033",
      "type": "dialogue",
      "ru": "«Вдобавок чтение заклинания в самый миг начала схватки. А у нас ни единого средства сопротивляться — эй, да это же тупик. Безвыходняк. Кусоге, каких поискать.»"
    },
    {
      "pid": "p57-0034",
      "type": "paragraph",
      "ru": "Вцепившись в волосы, он заново осознал, в сколь скверном положении очутился."
    },
    {
      "pid": "p57-0035",
      "type": "paragraph",
      "ru": "Малая толика светлых посылок, что только что забрезжила, разлетелась вдребезги, и мозг Субару закипел в поисках иного хода."
    },
    {
      "pid": "p57-0036",
      "type": "paragraph",
      "ru": "Состояние барона Асура: пол-лица посинело от безысходности, а другая половина побагровела от упрямого азарта. И вот такому Субару Беатрис —"
    },
    {
      "pid": "p57-0037",
      "type": "dialogue",
      "ru": "«Правда, это касается лишь сработавшего проклятия.»"
    },
    {
      "pid": "p57-0038",
      "type": "dialogue",
      "ru": "— словно раскрывая фокус, с размякшей в улыбке губой обронила она."
    },
    {
      "pid": "p57-0039",
      "type": "dialogue",
      "ru": "«А?» — выдохнул он и поднял голову; в глаза ему бросилась самодовольная мина Беатрис. На лице девочки читалось «ловко же ты попался», — но в груди у Субару всё насквозь промёрзло."
    },
    {
      "pid": "p57-0040",
      "type": "paragraph",
      "ru": "От чудовищной разницы температур, что возникла к этому мигу, Беатрис чуть растерянно захлопала глазами:"
    },
    {
      "pid": "p57-0041",
      "type": "dialogue",
      "ru": "«…Чего уж так-то злиться, я не пойму.»"
    },
    {
      "pid": "p57-0042",
      "type": "dialogue",
      "ru": "«Я. Сурьёзно. Больше. Молчу.»"
    },
    {
      "pid": "p57-0043",
      "type": "paragraph",
      "ru": "Едва выдавил он в ответ, по слогам убив в себе всякое чувство."
    },
    {
      "pid": "p57-0044",
      "type": "paragraph",
      "ru": "В груди бушевали брань и проклятия в адрес Беатрис, но выплёскивать их наружу и ссориться с ней теперь не хотелось."
    },
    {
      "pid": "p57-0045",
      "type": "paragraph",
      "ru": "Ведь как-никак наконец-то забрезжил проблеск светлой зацепки."
    },
    {
      "pid": "p57-0046",
      "type": "paragraph",
      "ru": "Словно беря себя в руки, Беатрис вскинула палец и, будто читая лекцию:"
    },
    {
      "pid": "p57-0047",
      "type": "dialogue",
      "ru": "«Как я уже сказала, от единожды сработавшего проклятия средства нет. Однако проклятию до его срабатывания помешать можно. До срабатывания это ещё не проклятие, а лишь заклинательная вязь, так что расплести её под силу любому существу с мало-мальским умением — дело пустяковое.»"
    },
    {
      "pid": "p57-0048",
      "type": "dialogue",
      "ru": "«Например?»"
    },
    {
      "pid": "p57-0049",
      "type": "dialogue",
      "ru": "«В этом особняке — перво-наперво Бетти. Само собой, Нии-чя. Ещё Розвааль и… а вот троим девчонкам, пожалуй, не под силу. А, тебе тоже не под силу.»"
    },
    {
      "pid": "p57-0050",
      "type": "dialogue",
      "ru": "«Это-то я на своей шкуре изведал…»"
    },
    {
      "pid": "p57-0051",
      "type": "paragraph",
      "ru": "И в первый раз, и во второй она ему по этой части изрядно «пособила»."
    },
    {
      "pid": "p57-0052",
      "type": "paragraph",
      "ru": "И, отставив это в сторону, Субару придвинулся к Беатрис:"
    },
    {
      "pid": "p57-0053",
      "type": "dialogue",
      "ru": "«А как распознать эту самую вязь до срабатывания? Вернее — выходит, что для проклятия нужна подготовка, прежде чем пустить его в ход?»"
    },
    {
      "pid": "p57-0054",
      "type": "dialogue",
      "ru": "«Само собой. Берёшься за сильную вязь — тяжелее и расплата для тебя самого. Со всем так. У проклятия эта сторона особенно сильна. Если помыслить о действии на человека, это закономерная цена.»"
    },
    {
      "pid": "p57-0055",
      "type": "dialogue",
      "ru": "«А эта… цена проклятия — её можно как-то прикинуть наперёд?»"
    },
    {
      "pid": "p57-0056",
      "type": "paragraph",
      "ru": "С таким чувством, будто хватаешься за соломинку, задал он вопрос; Беатрис прикрыла один глаз, призадумалась, облизнула губы:"
    },
    {
      "pid": "p57-0057",
      "type": "dialogue",
      "ru": "«Содержание меняется смотря по тому, проклятие с каким действием творят. Но есть правило, которое нипочём не обойти.»"
    },
    {
      "pid": "p57-0058",
      "type": "dialogue",
      "ru": "«Не обойти… правило…»"
    },
    {
      "pid": "p57-0059",
      "type": "paragraph",
      "ru": "Затаив дыхание, он поторопил её договорить начатое."
    },
    {
      "pid": "p57-0060",
      "type": "paragraph",
      "ru": "На мольбу в глазах Субару Беатрис чуть повела подбородком:"
    },
    {
      "pid": "p57-0061",
      "type": "dialogue",
      "ru": "«—Соприкосновение с тем, на кого творят проклятие. Вот непременное условие.»"
    },
    {
      "pid": "p57-0062",
      "type": "dialogue",
      "ru": "— так она и сказала."
    },
    {
      "pid": "p57-0063",
      "type": "paragraph",
      "ru": "В тот миг, как это улеглось у него в голове, мозг Субару закрутился с бешеной скоростью. Чтобы сотворить проклятие, нужно касание заклинателя и жертвы. А это значит, что и в первый раз, и во второй Субару сам сходился лицом к лицу с тем заклинателем. — Он принялся рыться в памяти, силясь припомнить этого человека."
    },
    {
      "pid": "p57-0064",
      "type": "dialogue",
      "ru": "«Если отбросить особняковую братию…»"
    },
    {
      "pid": "p57-0065",
      "type": "paragraph",
      "ru": "Исключив их, тех, что тоже могли стать мишенью проклятия, Субару перебрал в памяти первые восемь дней."
    },
    {
      "pid": "p57-0066",
      "type": "paragraph",
      "ru": "Время, когда он вёл житьё прислуги в особняке и почти не имел случая соприкоснуться с кем-либо, кроме здешних. И единственное внешнее, с кем Субару за это время мог соприкоснуться, —"
    },
    {
      "pid": "p57-0067",
      "type": "dialogue",
      "ru": "«—деревня у подножия.»"
    },
    {
      "pid": "p57-0068",
      "type": "paragraph",
      "ru": "И в первый раз, и во второй Субару наведывался в ту деревню."
    },
    {
      "pid": "p57-0069",
      "type": "paragraph",
      "ru": "И если припомнить, оба раза он ходил в деревню именно днём того самого, решающего четвёртого дня. В деревне заклинатель накладывает на него вязь проклятия, он той же ногой возвращается в особняк — и ворожба срабатывает, доводя до смерти: эта схема мелькнула у него в голове."
    },
    {
      "pid": "p57-0070",
      "type": "paragraph",
      "ru": "Если допустить, что заклинатель гостит в деревне, то понятно становится и тот случай в четвёртом круге, когда мишенью проклятия стала Рем."
    },
    {
      "pid": "p57-0071",
      "type": "paragraph",
      "ru": "В том круге она пошла в деревню — и просто-напросто её и выбрали целью заклинателя. При ином раскладе это могла оказаться Рам, а сунься туда сам Субару — так оно сталось бы с ним."
    },
    {
      "pid": "p57-0072",
      "type": "paragraph",
      "ru": "Сходится. Сходится. Всё — сошлось."
    },
    {
      "pid": "p57-0073",
      "type": "dialogue",
      "ru": "«Бэа-ко. Не знаешь, сколько примерно народу живёт в ближайшей к этому особняку деревне?»"
    },
    {
      "pid": "p57-0074",
      "type": "paragraph",
      "ru": "Огорошенная внезапной сменой темы, Беатрис недоумённо свела брови. Но, должно быть, оттого, что лицо Субару было слишком уж серьёзным, попрекать его этим она не стала и покачала головой:"
    },
    {
      "pid": "p57-0075",
      "type": "dialogue",
      "ru": "«Не знаю. Уж не обессудь, но Бетти, если не считать этого книгохранилища, и в самом-то особняке мало что разумеет.»"
    },
    {
      "pid": "p57-0076",
      "type": "dialogue",
      "ru": "«Вот как. Да нет, ничего. Это я уж лишку хочу. Да и такое-то я у Розвааля выспрошу — дело нехитрое… а дальше»"
    },
    {
      "pid": "p57-0077",
      "type": "paragraph",
      "ru": "Среди жителей ли заклинатель — или среди заезжих гостей."
    },
    {
      "pid": "p57-0078",
      "type": "paragraph",
      "ru": "Если второе — отыскать его не так уж и сложно. Знай себе расспрашивай деревенских да выкуривай заклинателя проклятий на свет. А вот если первое — вычислить его станет задачей непосильной. Если уж подготовились настолько обстоятельно, тут впору руки опустить, но —"
    },
    {
      "pid": "p57-0079",
      "type": "dialogue",
      "ru": "«Хотя такое — наоборот, навряд ли.»"
    },
    {
      "pid": "p57-0080",
      "type": "paragraph",
      "ru": "Если положить, что нынешнее дело завязано на королевский отбор, то истребление королевской семьи поветрием — событие всего лишь примерно полугодовой давности."
    },
    {
      "pid": "p57-0081",
      "type": "paragraph",
      "ru": "А если приплюсовать и то время, что ушло, пока Эмилию выдвинули в кандидатки на престол и пока сложили самую раму королевского отбора, — то нынешнее положение лишь только-только сладилось, за каких-нибудь три-четыре месяца: с пылу с жару побоище."
    },
    {
      "pid": "p57-0082",
      "type": "paragraph",
      "ru": "Не верилось, чтобы загодя сыскался некто столь прозорливый, чтобы заранее упрятать в деревне заклинателя проклятий. А если такой и нашёлся — то это либо провидец, либо тот, кто «знал о грядущем королевском отборе наперёд», иначе и не помыслить."
    },
    {
      "pid": "p57-0083",
      "type": "paragraph",
      "ru": "Стоит так рассудить —"
    },
    {
      "pid": "p57-0084",
      "type": "dialogue",
      "ru": "«Заклинатель — человек со стороны. И при этом отыскать его — задачка не больно-то высокой сложности…!»"
    },
    {
      "pid": "p57-0085",
      "type": "paragraph",
      "ru": "Проговорив это вслух, Субару принялся выискивать в собственной задумке прорехи."
    },
    {
      "pid": "p57-0086",
      "type": "paragraph",
      "ru": "Несколько поправок, правда, набиралось, но в общих чертах рассуждение было недурно. К тому же со стороны заклинателя это пора, когда он ещё не начал действовать. А что в этот самый миг его существование уже раскрыто — такого, кроме как богу или дьяволу, никому не дано знать."
    },
    {
      "pid": "p57-0087",
      "type": "paragraph",
      "ru": "Вскинув голову, он повёл взглядом в поисках часов — но их не было."
    },
    {
      "pid": "p57-0088",
      "type": "paragraph",
      "ru": "Цокнув языком, он, однако, вспомнил давешний замер по «таймеру-щетине» и вгрызся в тот факт, что сейчас всё ещё «ночь второго дня»."
    },
    {
      "pid": "p57-0089",
      "type": "paragraph",
      "ru": "Против четвёртого дня, с которого положение начнёт клониться к худшему, в запасе ещё целые сутки."
    },
    {
      "pid": "p57-0090",
      "type": "paragraph",
      "ru": "А это, иными словами, означает, что и с его стороны нападение на заклинателя врасплох становится возможным."
    },
    {
      "pid": "p57-0091",
      "type": "dialogue",
      "ru": "«Ухватил за хвост, чёрт дери…! Не зря же меня раз прикончили да раз чуть не прикончили, сволочи!»"
    },
    {
      "pid": "p57-0092",
      "type": "paragraph",
      "ru": "Забрезжил свет. Положение меняется."
    },
    {
      "pid": "p57-0093",
      "type": "paragraph",
      "ru": "Безысходность будто распахнулась, и с той стороны хлынул луч надежды, — и Субару, сам того не замечая, сжал кулак и задрожал голосом от восторга."
    },
    {
      "pid": "p57-0094",
      "type": "paragraph",
      "ru": "А вот Беатрис, что с какого-то момента осталась за бортом этой радости по поводу перелома в делах, была недовольна."
    },
    {
      "pid": "p57-0095",
      "type": "paragraph",
      "ru": "Зардевшись своими прелестными щеками, она надула губы, выказывая досаду:"
    },
    {
      "pid": "p57-0096",
      "type": "dialogue",
      "ru": "«Просить у человека подмоги — и этакое обхождение, это уж ни в какие ворота. Раз нынешний разговор пошёл тебе впрок, так Бетти есть что сказать, разве нет?»"
    },
    {
      "pid": "p57-0097",
      "type": "dialogue",
      "ru": "«Ага, верно! Выручила, благодаря тебе я свет увидел! Бэа-ко, безумно тебя люблю!»"
    },
    {
      "pid": "p57-0098",
      "type": "dialogue",
      "ru": "«Ка-а—?!»"
    },
    {
      "pid": "p57-0099",
      "type": "paragraph",
      "ru": "Подскочив, он сунул руки ей под мышки, поднял лёгонькое тельце и, вознеся Беатрис над головой, закружился волчком."
    },
    {
      "pid": "p57-0100",
      "type": "paragraph",
      "ru": "Хоть и облачена она была в роскошное платье, тело девочки было лёгким, точно пёрышко. Субару и сам был на седьмом небе, так что от такого сложения сил скорость вращения помножилась вдвое, а там и ещё вдвое."
    },
    {
      "pid": "p57-0101",
      "type": "dialogue",
      "ru": "«Пус-… опусти сейчас же!»"
    },
    {
      "pid": "p57-0102",
      "type": "dialogue",
      "ru": "«Ха-ха-ха, сейчас я, кажись, и в небо взлечу. А то давай-ка вместе полетим, Бэа-ко?! Ай кэн флай! Ю кэн флай!»"
    },
    {
      "pid": "p57-0103",
      "type": "dialogue",
      "ru": "«Не зарывайся, кому говорю—!»"
    },
    {
      "pid": "p57-0104",
      "type": "dialogue",
      "ru": "«Джамп-про?!»"
    },
    {
      "pid": "p57-0105",
      "type": "paragraph",
      "ru": "Прямо сверху, с ближнего расстояния, шарахнуло магической силой, и от прямого попадания его впечатало в пол в какой-то несусветной позе."
    },
    {
      "pid": "p57-0106",
      "type": "paragraph",
      "ru": "Удар, ворвавшийся через макушку, прошёл по телу и вышел ровнёхонько через зад. Шлёпнувшись на пятую точку, он закатил глаза от бурлящего внутри потока маны."
    },
    {
      "pid": "p57-0107",
      "type": "paragraph",
      "ru": "Беатрис же, та, что всё это устроила, высвободилась из хватки Субару и своим крошечным тельцем вычертила в воздухе изящную параболу."
    },
    {
      "pid": "p57-0108",
      "type": "paragraph",
      "ru": "Но тело девочки, что, казалось, вот-вот куда-нибудь врежется, вдруг застыло в воздухе. Легко перевернувшись и взметнув подол, она с прямо-таки изысканной невозмутимостью невесомо опустилась на пол книгохранилища."
    },
    {
      "pid": "p57-0109",
      "type": "paragraph",
      "ru": "Она глянула сверху вниз на Субару, что всё ещё неприглядно мотал головой, лёжа на полу, и, привычно фыркнув:"
    },
    {
      "pid": "p57-0110",
      "type": "dialogue",
      "ru": "«Вот потому, что ты этак зарываешься и распускаешь себя, и получаешь по шее.»"
    },
    {
      "pid": "p57-0111",
      "type": "dialogue",
      "ru": "«Получил-то я не только это. — Было бело.»"
    },
    {
      "pid": "p57-0112",
      "type": "dialogue",
      "ru": "«—?! Ну держи!»"
    },
    {
      "pid": "p57-0113",
      "type": "dialogue",
      "ru": "«Доровас?!»"
    },
    {
      "pid": "p57-0114",
      "type": "paragraph",
      "ru": "Второй выстрел прямёхонько влепил ему в подбородок и легко зашвырнул в самую глубь книгохранилища. Прокатившись кубарем, он врезался в стремянку и оказался погребён под валящимися сверху досками. Угловатые края тыкались куда попало, и от несусветной боли на глазах у него выступили слёзы:"
    },
    {
      "pid": "p57-0115",
      "type": "dialogue",
      "ru": "«Стоило шкале приязни выскочить за край да выйти супер-приёму — и вот тебе раз! Чем ты недовольна-то была, ну-ка скажи!»"
    },
    {
      "pid": "p57-0116",
      "type": "dialogue",
      "ru": "«И тем, что ты на меня кинулся, и тем, что поднял, как дитя малое, и тем, что вертел туда-сюда, и тем, что бельё подсмотрел, и тем, что наплёл пустых, для виду, слов о любви, — всем разом! Да у меня уже от одного твоего существования всё внутри кипит!»"
    },
    {
      "pid": "p57-0117",
      "type": "dialogue",
      "ru": "«Полное отрицание моего существования — это же горько, прекрати! Прямо времена хикикомори вспоминаются, хоть оно и не так уж давно было.»"
    },
    {
      "pid": "p57-0118",
      "type": "paragraph",
      "ru": "Времена затворничества, до которых, чудилось, теперь рукой не достать."
    },
    {
      "pid": "p57-0119",
      "type": "paragraph",
      "ru": "И впрямь, по расстоянию-то его занесло уже невесть в какую даль, не сосчитать; так как вы там, любезные читатели, все ли в добром здравии?"
    },
    {
      "pid": "p57-0120",
      "type": "paragraph",
      "ru": "Так или иначе,"
    },
    {
      "pid": "p57-0121",
      "type": "dialogue",
      "ru": "«Один круг сделал — и поостыл; а ведь положение-то изрядно полегчало. …Этой ночью, ясное дело, тяжко, но завтра примерно наведаюсь в деревню» —"
    },
    {
      "pid": "p57-0122",
      "type": "paragraph",
      "ru": "и дознаюсь, кто таков заклинатель, решил он."
    },
    {
      "pid": "p57-0123",
      "type": "paragraph",
      "ru": "В одиночку пойти, скорее всего, не выйдет, так что придётся идти в паре — либо с Рам, либо с Рем. А коль скоро на месте не исключено и столкновение с заклинателем, то участие этих двоих, искусных в бою, казалось непременным условием."
    },
    {
      "pid": "p57-0124",
      "type": "paragraph",
      "ru": "Если повезёт — заклинателя одолеть, а если повезёт сверх того — выяснить, что отношения Субару с этим заклинателем чисты, как лист, и тогда дело завершится всеобщим торжеством."
    },
    {
      "pid": "p57-0125",
      "type": "paragraph",
      "ru": "Прохождение Миссии 2 «Возьми приступом особняк Розвааля»."
    },
    {
      "pid": "p57-0126",
      "type": "dialogue",
      "ru": "«По сравнению с Миссией 1 сложность была реально запредельная, честное слово.»"
    },
    {
      "pid": "p57-0127",
      "type": "paragraph",
      "ru": "Миссия 1, помнится, кажется, была «Одолей шпану», так что, как ни оглянись, занесло его и впрямь далеко."
    },
    {
      "pid": "p57-0128",
      "type": "paragraph",
      "ru": "Припомнив незаметно отдалившуюся в прошлое возню со шпаной, он заново перебрал в памяти дни в особняке."
    },
    {
      "pid": "p57-0129",
      "type": "paragraph",
      "ru": "Понимал, что радоваться рано, и всё же — глухой тупик, где прежде ни рукой ни ногой было не двинуть, наконец-то, кажется, раскрывался. Уж этакую-то малость восторга пусть ему простят."
    },
    {
      "pid": "p57-0130",
      "type": "paragraph",
      "ru": "Нет ли ещё чего, что непременно надо бы уладить, — Субару не позволял себе небрежения, проверяя почву под ногами."
    },
    {
      "pid": "p57-0131",
      "type": "paragraph",
      "ru": "Именно потому, что дело пошло на лад, и закрадывалось подозрение: а нет ли там западни? Настороженность от малодушия; но в эту-то сторожевую сеть вдруг и зацепилось одно словцо. То самое —"
    },
    {
      "pid": "p57-0132",
      "type": "dialogue",
      "ru": "«Ведьмин… смрад…»"
    },
    {
      "pid": "p57-0133",
      "type": "dialogue",
      "ru": "«Что такое?»"
    },
    {
      "pid": "p57-0134",
      "type": "dialogue",
      "ru": "«Точно. Ведьма. И Рем тоже…»"
    },
    {
      "pid": "p57-0135",
      "type": "paragraph",
      "ru": "Стоит сплести одно это словцо — и в памяти оживает череда сцен."
    },
    {
      "pid": "p57-0136",
      "type": "paragraph",
      "ru": "Слово «ведьма», что всплывало в них повсюду, — истинного его смысла Субару как знания пока так и не обрёл."
    },
    {
      "pid": "p57-0137",
      "type": "paragraph",
      "ru": "Ведьма этого мира, что ведома Субару, — лишь персонаж предельно короткой побасенки под названием «Ведьма зависти», что значилась там как сказочка. Однако, если припомнить, и в петле первого дня по призыву, и здесь, в повторах в особняке, это имя нет-нет да и казало лицо."
    },
    {
      "pid": "p57-0138",
      "type": "paragraph",
      "ru": "Субару поднял голову и глянул на Беатрис, что недоумённо свела брови."
    },
    {
      "pid": "p57-0139",
      "type": "paragraph",
      "ru": "Кольнула лёгкая тревога: ответит ли она? Ведь как-никак в прошлый раз, стоило ему это произнести, Рам отрезала наотмашь, а Рем так и вовсе сделала из этого повод наброситься. Даже та самая Эмилия, помнилось, противилась этому с какой-то силой. А потому, неся в себе эту тревогу,"
    },
    {
      "pid": "p57-0140",
      "type": "dialogue",
      "ru": "«Бэа-ко. — Ведьму… знаешь?»"
    },
    {
      "pid": "p57-0141",
      "type": "dialogue",
      "ru": "«——»"
    },
    {
      "pid": "p57-0142",
      "type": "paragraph",
      "ru": "На вопрос ответа тотчас не последовало."
    },
    {
      "pid": "p57-0143",
      "type": "paragraph",
      "ru": "Беатрис прикрыла глаза перед словом, всколыхнувшим барабанные перепонки, и смолкла, будто на вкус пробуя это слово."
    },
    {
      "pid": "p57-0144",
      "type": "paragraph",
      "ru": "Субару же, с растревоженным её откликом сердцем, лишь напряжённо выжидал."
    },
    {
      "pid": "p57-0145",
      "type": "paragraph",
      "ru": "Уж не задело ли, чего доброго, и нынешнее словцо её сокровенных струн —"
    },
    {
      "pid": "p57-0146",
      "type": "dialogue",
      "ru": "«Та, что выпивает мир досуха. Королева теневого замка. — Ведьма Зависти.»"
    },
    {
      "pid": "p57-0147",
      "type": "paragraph",
      "ru": "От внезапно оброненных слов Субару, затаив дыхание, широко раскрыл глаза."
    },
    {
      "pid": "p57-0148",
      "type": "paragraph",
      "ru": "Не беря в расчёт этой его реакции, Беатрис уронила с губ тоскливый вздох:"
    },
    {
      "pid": "p57-0149",
      "type": "dialogue",
      "ru": "«В этом мире слово „ведьма“ указывает лишь на одно-единственное существо. И существо это таково, что само его поминание почитается за запрет.»"
    },
    {
      "pid": "p57-0150",
      "type": "dialogue",
      "ru": "«Все её страшатся, все пред ней благоговеют, все ей перечить не смеют.»"
    },
    {
      "pid": "p57-0151",
      "type": "dialogue",
      "ru": "«Да, оно самое. Скорее уж сам твой вопрос — знаю ли я — и есть диво. Не знать её попросту немыслимо. В этом мире после имени родителей, после имён родни третьим затверживают имя той ведьмы.»"
    },
    {
      "pid": "p57-0152",
      "type": "dialogue",
      "ru": "«Ну уж это ты хватила, преувеличиваешь…»"
    },
    {
      "pid": "p57-0153",
      "type": "paragraph",
      "ru": "Он было собрался отмахнуться смехом, но, не сыскав на лице Беатрис ни крупицы шутки, проглотил слова."
    },
    {
      "pid": "p57-0154",
      "type": "paragraph",
      "ru": "Если нынешнее — не шутка, то это, без всякого преувеличения, тот самый символ, что мир обязан проклинать, —"
    },
    {
      "pid": "p57-0155",
      "type": "dialogue",
      "ru": "«Ведьма Зависти „Сатэла“. — Худшее из бедствий, что пожрало всех шестерых ведьм, носивших имена смертных грехов, и сгубило половину мира.»"
    },
    {
      "pid": "p57-0156",
      "type": "paragraph",
      "ru": "Промолвив это голосом, в котором застыло всякое чувство, Беатрис так и прикрыла глаза."
    },
    {
      "pid": "p57-0157",
      "type": "paragraph",
      "ru": "От этого имени, что отдавалось чем-то знакомым, Субару коротко выдохнул «ха», и тяжесть впечатанного имени сковала его так, что и шелохнуться было нельзя."
    },
    {
      "pid": "p57-0158",
      "type": "dialogue",
      "ru": "«Сказывают, она властвовала над ночью. Сказывают, ей не внятна человеческая речь. Сказывают, она завидовала всему на этом свете. Сказывают, никто, узревший её лик, не уцелел. Сказывают, тело её вовек не истлеет, не одряхлеет, не ведает конца. Сказывают, силою дракона, героя и мудреца её удалось запечатать, но сгубить её — так и не вышло.»"
    },
    {
      "pid": "p57-0159",
      "type": "paragraph",
      "ru": "Без умолку перечисляя это, Беатрис не давала Субару вставить и слова."
    },
    {
      "pid": "p57-0160",
      "type": "paragraph",
      "ru": "И, словно подводя черту под нанизанными сведениями, поставив последнее предисловие — «Сказывают», — она произнесла:"
    },
    {
      "pid": "p57-0161",
      "type": "dialogue",
      "ru": "«—Тело её было серебровласой полуэльфийкой.»"
    }
  ],
  "partInChapter": 33
}
